finstat/__init__.py
finstat/base.py
finstat/groupers.py
finstat/optimize.py
finstat/statement.py
finstat/valuation.py
finstat/elements/__init__.py
finstat/elements/elements.py
finstat/elements/lineitem.py
finstat/elements/schedules.py
finstat/functions/__init__.py
finstat/functions/arr.py
finstat/functions/base.py
finstat-0.11.3.dist-info/LICENSE
finstat-0.11.3.dist-info/METADATA
finstat-0.11.3.dist-info/WHEEL
finstat-0.11.3.dist-info/top_level.txt
finstat-0.11.3.dist-info/RECORD
